crawlbyte/__init__.py
crawlbyte/client.py
crawlbyte/sdk.py
crawlbyte/types.py
crawlbyte_sdk-1.0.1.dist-info/METADATA
crawlbyte_sdk-1.0.1.dist-info/WHEEL
crawlbyte_sdk-1.0.1.dist-info/top_level.txt
crawlbyte_sdk-1.0.1.dist-info/RECORD
