Metadata-Version: 2.4
Name: crawlbyte-sdk
Version: 1.0.1
Summary: Official Python SDK for Crawlbyte – create tasks, poll results, and integrate data scraping into your Python applications.
Home-page: https://crawlbyte.ai
Author: Crawlbyte
Author-email: Crawlbyte <marek@crawlbyte.ai>
License: MIT
Project-URL: Homepage, https://crawlbyte.ai
Project-URL: Documentation, https://developers.crawlbyte.ai
Keywords: crawlbyte,scraping,sdk
Requires-Python: >=3.7
